cassandra_joinlib/__init__.py
cassandra_joinlib/commands.py
cassandra_joinlib/file_utils.py
cassandra_joinlib/hash_join.py
cassandra_joinlib/intermediate_result.py
cassandra_joinlib/join_executor.py
cassandra_joinlib/math_utils.py
cassandra_joinlib/nested_join.py
cassandra_joinlib/utils.py
cassandra_joinlib-0.3.1.dist-info/LICENSE
cassandra_joinlib-0.3.1.dist-info/METADATA
cassandra_joinlib-0.3.1.dist-info/WHEEL
cassandra_joinlib-0.3.1.dist-info/top_level.txt
cassandra_joinlib-0.3.1.dist-info/RECORD
